gvcode/__init__.py
gvcode/compat.py
gvcode/main.py
gvcode/resource/fonts/simsun.ttc
graphic_verification_code-1.1.1.dist-info/METADATA
graphic_verification_code-1.1.1.dist-info/WHEEL
graphic_verification_code-1.1.1.dist-info/top_level.txt
graphic_verification_code-1.1.1.dist-info/RECORD
