Metadata-Version: 2.1
Name: graphic-verification-code
Version: 1.1.1
Summary: Graphic Verification Code
Home-page: https://github.com/Brightcells/graphic-verification-code
Author: Hackathon
Author-email: kimi.huang@brightcells.com
Keywords: Graphic Verification Code
Classifier: License :: OSI Approved :: BSD License
Classifier: Programming Language :: Python
Classifier: Programming Language :: Python :: 2
Classifier: Programming Language :: Python :: 2.5
Classifier: Programming Language :: Python :: 2.6
Classifier: Programming Language :: Python :: 2.7
Classifier: Programming Language :: Python :: 3
Classifier: Programming Language :: Python :: 3.2
Classifier: Programming Language :: Python :: 3.3
Classifier: Programming Language :: Python :: 3.4
Classifier: Topic :: Software Development :: Libraries :: Python Modules
Requires-Dist: Pillow (>=9.2.0)
